{
  "schema": "srmod/1",
  "id": "FairansVision/FPBR_WaterEdition",
  "source": "redux/community_mods",
  "name": "FPBR_WaterEdition",
  "title": "FPBR_WaterEdition",
  "author": "LEOPARD, Fairan, Marshalska Rokossovsky",
  "section": "Fairan's Vision",
  "priority": "10",
  "description": "Масштабный ребаланс планетарных боёв (форк LEOPBRebalance)",
  "full_description": "Отличия от LEOPBRebalance:\n- Изменены хп турелей: повышено у пулеметной пушки, уменьшено у тяжелой, ракетной и существенно уменьшено у лазерной.\n- Увеличено время перезарядки тяжелой турели, незначительно увеличен урон.\n- В несколько раз увеличен урон лазерной турели, снижен ее радиус атаки.\n- Увеличен урон лазеров.\n- Увеличен урон пулемета, существенно снижена дальность, стоимость повышена.\n- Увеличен урон гранатомета, перезарядка и его стоимость.\n- Пулеметная турель заменена на разрядную.\n- Повышены хп экраноплана.\n- Уменьшены хп антигравов, повышена их скорость.\n- Повышены хп трайдента.\n- Уменьшены хп фуллстека.\n<clr><clrEnd>\nСпециальная версия для водных карт - всем шаблонам для ИИ ходовая часть заменена на ту, которая может летать по воде, иначе у ИИ происходят затупы и карты становятся чрезмерно лёгкими.",
  "version": "249ffe18bf60a370",
  "depends": [],
  "conflicts": [
    "LEOPBRebalance",
    "FairanPBRebalance",
    "FairanPBShablons"
  ],
  "chunk_index_url": "https://huggingface.co/datasets/Artyudin/sr-mods-assets/resolve/main/asset_index.json",
  "files": {
    "code": {
      "Community Mods_unpacked/Mods/FairansVision/FPBR_WaterEdition/ModuleInfo.txt": {
        "sha256": "65c425d6e002f739db50aec237940a83b2bd648ff93c45f215561443161630dc",
        "size": 5450
      },
      "Community Mods_unpacked/Mods/FairansVision/FPBR_WaterEdition/CFG/Rus/Lang.dat": {
        "sha256": "dafe4e9bcca288a82ec4b6e0f49ad3e53439ca05dcfb2448d218cd0f8b1ba72f",
        "size": 73
      },
      "Community Mods_unpacked/Mods/FairansVision/FPBR_WaterEdition/CFG/Rus/Robots/data.txt": {
        "sha256": "4b85e363b77c015e7a5cb2846f7c5c3e7ca98e59817a2a1ff286d369aa2a0d99",
        "size": 36942
      },
      "Community Mods_unpacked/Mods/FairansVision/FPBR_WaterEdition/CFG/Rus/Robots/iface.txt": {
        "sha256": "cc781cf6ce351dd455f57172039e60c0d01ab2522af023c3081407d29abfa849",
        "size": 2595
      },
      "Community Mods_unpacked/Mods/FairansVision/FPBR_WaterEdition/CFG/Rus/Robots/Бэкап/data.txt": {
        "sha256": "6a067b705ddcb3a7f010494f5a9460895afa2a0cbee3a39e800eb0fcf341a7bc",
        "size": 24668
      },
      "Community Mods_unpacked/Mods/FairansVision/FPBR_WaterEdition/CFG/Rus/Robots/До баланса ресурсов/data.txt": {
        "sha256": "491c459ac478507ef3185efd8f408638852d93026820683106c16d506ecffb9e",
        "size": 24856
      }
    },
    "assets": {}
  }
}